azure/common/__init__.py
azure/common/_version.py
azure/common/client_factory.py
azure/common/cloud.py
azure/common/credentials.py
azure/common/exceptions.py
azure/profiles/__init__.py
azure/profiles/multiapiclient.py
azure_common-1.1.27.dist-info/METADATA
azure_common-1.1.27.dist-info/WHEEL
azure_common-1.1.27.dist-info/top_level.txt
azure_common-1.1.27.dist-info/RECORD
